Workbook
Name SegmentaciónDeDatos_CATEGORIA: #N/A
Name SegmentaciónDeDatos_REGION: #N/A
Name SegmentaciónDeDatos_TOTAL_VENTA: #N/A
Name SegmentaciónDeDatos_TOTAL_VENTA1: #N/A
Name SegmentaciónDeDatos_VENDEDOR: #N/A

Sheet PORTADA
F6: Título: "Proyecto Final - Curso de Excel".
F8: Nombre: Romina Ríos.
F10: Febrero 2025.

Sheet README
A3: Información del Proyecto: Análisis de ventas y desempeño de productos de tecnología para la toma de decisiones comerciales.
A5: Objetivo: Aplicar herramientas avanzadas de Excel para transformar datos brutos en un Dashboard interactivo que responda a preguntas de negocio.
A7: Fuente de los Datos: Dataset de ventas de tecnología (período 2023-2024).
A9: Versión de Excel utilizada: Microsoft Excel 2021.
A12: Criterios de Análisis y Pasos realizados:
A14: Depuración: Limpieza de duplicados y normalización de formatos en la Tabla Principal.
A16: Enriquecimiento: Creación de columnas calculadas usando funciones lógicas (SI, Y, O) y de búsqueda (BUSCARX o BUSCARV).
A18: Procesamiento: Generación de Tablas Dinámicas para agrupar ventas por categoría y país.
A20: Visualización: Diseño de un Dashboard con segmentadores de datos para permitir filtros rápidos por el usuario final.

Sheet PREGUNTAS Y RESPUESTAS
A1: ANALISIS DE DATOS
B4: Pregunta Central | C4: Objetivo de Negocio | D4: Herramienta / Resolución
B5: 1. ¿Cuál es el rendimiento de ventas por categoría? | C5: Identificar los productos estrella que generan más ingresos. | D5: Tabla Dinámica + Gráfico de Barras.
B6: 2. ¿Cómo se distribuyen las ventas por país? | C6: Determinar la presencia de mercado en cada región. | D6: Función SUMAR.SI.CONJUNTO y Segmentadores.
B7: 3. ¿Qué pedidos requieren gestión de envío prioritaria? | C7: Optimizar la logística para productos de alto valor. | D7: Función SI anidada (SI con Y).
B9: 4. ¿Cuál es el precio promedio por categoría? | C9: Analizar el posicionamiento de precios en el catálogo. | D9: Función PROMEDIO.SI + Gráfico Circular.

Sheet DATASET ORIGINAL
B2: ID_VENTA | C2: FECHA | D2: VENDEDOR | E2: PRODUCTO | F2: CATEGORIA | G2: REGION | H2: CANTIDAD | I2: PRECIO_UNITARIO | J2: DESCUENTO | K2: TOTAL_VENTA
B3: 1 | C3: 01/017/2024 | D3: CARLOS | E3: Producto | F3: Categoría | G3: Norte | H3: 11 | I3: 1725 | J3: =RANDBETWEEN(0, 15) / 100 -> 0.12 | K3: =H3*I3 -> 18975
B4: 2 | C4: 01/017/2025 | D4: LUIS | E4: Celular Samsung | F4: Tecnología | G4: Sur | H4: 2 | I4: 557 | J4: =RANDBETWEEN(0, 15) / 100 -> 0.02 | K4: =H4*I4 -> 1114
B5: 3 | C5: 01/017/2026 | D5: PEDRO | E5: Cafetera Eléctrica | F5: Hogar | G5: Centro | H5: 2 | I5: 1305 | J5: =RANDBETWEEN(0, 15) / 100 -> 0.1 | K5: =H5*I5 -> 2610
B6: 4 | C6: 01/017/2027 | D6: OSCAR | E6: Monitor 24" | F6: Oficina | G6: Este | H6: 16 | I6: 4398 | J6: =RANDBETWEEN(0, 15) / 100 -> 0.11 | K6: =H6*I6 -> 70368
B7: 5 | C7: 01/017/2028 | D7: JUAN | E7: Auriculares Bluetooth | F7: Tecnología | G7: Oeste | H7: 1 | I7: 3882 | J7: =RANDBETWEEN(0, 15) / 100 -> 0.13 | K7: =H7*I7 -> 3882
B8: 6 | C8: 01/017/2029 | D8: CARLOS | E8: Aspiradora Robot | F8: Hogar | G8: Norte | H8: 20 | I8: 4622 | J8: =RANDBETWEEN(0, 15) / 100 -> 0.15 | K8: =H8*I8 -> 92440
B9: 7 | C9: 01/017/2030 | D9: LUIS | E9: Silla Ergonómica | F9: Oficina | G9: Sur | H9: 2 | I9: 4911 | J9: =RANDBETWEEN(0, 15) / 100 -> 0.12 | K9: =H9*I9 -> 9822
B10: 8 | C10: 01/017/2031 | D10: PEDRO | E10: Tablet Lenovo | F10: Tecnología | G10: Centro | H10: 13 | I10: 1347 | J10: =RANDBETWEEN(0, 15) / 100 -> 0.02 | K10: =H10*I10 -> 17511
B11: 9 | C11: 01/017/2032 | D11: OSCAR | E11: Licuadora de Mano | F11: Hogar | G11: Este | H11: 19 | I11: 3782 | J11: =RANDBETWEEN(0, 15) / 100 -> 0.03 | K11: =H11*I11 -> 71858
B12: 10 | C12: 01/017/2033 | D12: JUAN | E12: Teclado Mecánico | F12: Oficina | G12: Oeste | H12: 5 | I12: 2020 | J12: =RANDBETWEEN(0, 15) / 100 -> 0.15 | K12: =H12*I12 -> 10100
B13: 11 | C13: 01/017/2034 | D13: CARLOS | E13: Smart TV 50" | F13: Tecnología | G13: Norte | H13: 14 | I13: 1073 | J13: =RANDBETWEEN(0, 15) / 100 -> 0.01 | K13: =H13*I13 -> 15022
B14: 12 | C14: 01/017/2035 | D14: LUIS | E14: Producto | F14: Categoría | G14: Sur | H14: 16 | I14: 524 | J14: =RANDBETWEEN(0, 15) / 100 -> 0.15 | K14: =H14*I14 -> 8384
... B504: 502 | C504: 01/017/2525 | D504: LUIS | E504: Silla Ergonómica | F504: Oficina | G504: Sur | H504: 12 | I504: 1313 | J504: =RANDBETWEEN(0, 15) / 100 -> 0.13 | K504: =H504*I504 -> 15756

Sheet TABLA PRINCIPAL
A1: ID_VENTA | B1: FECHA | C1: VENDEDOR | D1: PRODUCTO | E1: CATEGORIA | F1: REGION | G1: CANTIDAD | H1: PRECIO_UNITARIO | I1: DESCUENTO | J1: TOTAL_VENTA | K1: CALIFICACION | L1: PROVEEDOR | M1: PRIORIDAD DE ENVIO | N1: ID ALMACEN
A2: 176 | B2: 45467 | C2: CARLOS | D2: Smart TV 50" | E2: Tecnología | F2: Norte | G2: 2 | H2: 4997 | I2: 0.04 | J2: =G2*H2 -> 9994 | K2: =IF(J2>5000, "Venta Grande", "Venta Normal") -> Venta Grande | L2: =VLOOKUP(D2, AUXILIAR!$A$2:$B$16, 2, 0) -> LG Electronics | M2: =IF(AND(E2="Tecnología", J2>20000), "Prioridad Alta", IF(J2>5000, "Prioridad Media", "Prioridad Baja")) -> Prioridad Media | N2: =VLOOKUP(E2, AUXILIAR!$E$2:$F$4, 2, FALSE) -> ALM-01
A3: 2 | B3: 45293 | C3: LUIS | D3: Celular Samsung | E3: Tecnología | F3: Sur | G3: 2 | H3: 557 | I3: 0.08 | J3: =G3*H3 -> 1114 | K3: =IF(J3>5000, "Venta Grande", "Venta Normal") -> Venta Normal | L3: =VLOOKUP(D3, AUXILIAR!$A$2:$B$16, 2, 0) -> Samsung Oficial
A4: 3 | B4: 45294 | C4: PEDRO | D4: Cafetera Eléctrica | E4: Hogar | F4: Centro | G4: 2 | H4: 1305 | I4: 0.04 | J4: =G4*H4 -> 2610 | K4: =IF(J4>5000, "Venta Grande", "Venta Normal") -> Venta Normal | L4: =VLOOKUP(D4, AUXILIAR!$A$2:$B$16, 2, 0) -> LG Electronics
A5: 90 | B5: 45381 | C5: JUAN | D5: Celular Samsung | E5: Tecnología | F5: Oeste | G5: 8 | H5: 4971 | I5: 0.11 | J5: =G5*H5 -> 39768 | K5: =IF(J5>5000, "Venta Grande", "Venta Normal") -> Venta Grande | L5: =VLOOKUP(D5, AUXILIAR!$A$2:$B$16, 2, 0) -> Samsung Oficial | M5: =IF(AND(E5="Tecnología", J5>20000), "Prioridad Alta", IF(J5>5000, "Prioridad Media", "Prioridad Baja")) -> Prioridad Alta | N5: =VLOOKUP(E5, AUXILIAR!$E$2:$F$4, 2, FALSE) -> ALM-01
A6: 5 | B6: 45296 | C6: JUAN | D6: Auriculares Bluetooth | E6: Tecnología | F6: Oeste | G6: 1 | H6: 3882 | I6: 0.01 | J6: =G6*H6 -> 3882 | K6: =IF(J6>5000, "Venta Grande", "Venta Normal") -> Venta Normal | L6: =VLOOKUP(D6, AUXILIAR!$A$2:$B$16, 2, 0) -> LG Electronics
A7: 457 | B7: 45748 | C7: LUIS | D7: Aspiradora Robot | E7: Hogar | F7: Sur | G7: 4 | H7: 4967 | I7: 0.12 | J7: =G7*H7 -> 19868 | K7: =IF(J7>5000, "Venta Grande", "Venta Normal") -> Venta Grande | L7: =VLOOKUP(D7, AUXILIAR!$A$2:$B$16, 2, 0) -> Samsung Oficial | M7: =IF(AND(E7="Tecnología", J7>20000), "Prioridad Alta", IF(J7>5000, "Prioridad Media", "Prioridad Baja")) -> Prioridad Media | N7: =VLOOKUP(E7, AUXILIAR!$E$2:$F$4, 2, FALSE) -> ALM-02
A8: 170 | B8: 45461 | C8: JUAN | D8: Auriculares Bluetooth | E8: Tecnología | F8: Oeste | G8: 10 | H8: 4964 | I8: 0.03 | J8: =G8*H8 -> 49640 | K8: =IF(J8>5000, "Venta Grande", "Venta Normal") -> Venta Grande | L8: =VLOOKUP(D8, AUXILIAR!$A$2:$B$16, 2, 0) -> LG Electronics | M8: =IF(AND(E8="Tecnología", J8>20000), "Prioridad Alta", IF(J8>5000, "Prioridad Media", "Prioridad Baja")) -> Prioridad Alta | N8: =VLOOKUP(E8, AUXILIAR!$E$2:$F$4, 2, FALSE) -> ALM-01
A9: 140 | B9: 45431 | C9: JUAN | D9: Tablet Lenovo | E9: Tecnología | F9: Oeste | G9: 14 | H9: 4961 | I9: 0.07 | J9: =G9*H9 -> 69454 | K9: =IF(J9>5000, "Venta Grande", "Venta Normal") -> Venta Grande | L9: =VLOOKUP(D9, AUXILIAR!$A$2:$B$16, 2, 0) -> Office Design | M9: =IF(AND(E9="Tecnología", J9>20000), "Prioridad Alta", IF(J9>5000, "Prioridad Media", "Prioridad Baja")) -> Prioridad Alta | N9: =VLOOKUP(E9, AUXILIAR!$E$2:$F$4, 2, FALSE) -> ALM-01
A10: 97 | B10: 45388 | C10: LUIS | D10: Licuadora de Mano | E10: Hogar | F10: Sur | G10: 9 | H10: 4932 | I10: 0.03 | J10: =G10*H10 -> 44388 | K10: =IF(J10>5000, "Venta Grande", "Venta Normal") -> Venta Grande | L10: =VLOOKUP(D10, AUXILIAR!$A$2:$B$16, 2, 0) -> LG Electronics | M10: =IF(AND(E10="Tecnología", J10>20000), "Prioridad Alta", IF(J10>5000, "Prioridad Media", "Prioridad Baja")) -> Prioridad Media | N10: =VLOOKUP(E10, AUXILIAR!$E$2:$F$4, 2, FALSE) -> ALM-02
A11: 96 | B11: 45387 | C11: CARLOS | D11: Tablet Lenovo | E11: Tecnología | F11: Norte | G11: 8 | H11: 4912 | I11: 0.12 | J11: =G11*H11 -> 39296 | K11: =IF(J11>5000, "Venta Grande", "Venta Normal") -> Venta Grande | L11: =VLOOKUP(D11, AUXILIAR!$A$2:$B$16, 2, 0) -> Office Design | M11: =IF(AND(E11="Tecnología", J11>20000), "Prioridad Alta", IF(J11>5000, "Prioridad Media", "Prioridad Baja")) -> Prioridad Alta | N11: =VLOOKUP(E11, AUXILIAR!$E$2:$F$4, 2, FALSE) -> ALM-01
A12: 7 | B12: 45298 | C12: LUIS | D12: Silla Ergonómica | E12: Oficina | F12: Sur | G12: 2 | H12: 4911 | I12: 0.11 | J12: =G12*H12 -> 9822 | K12: =IF(J12>5000, "Venta Grande", "Venta Normal") -> Venta Grande | L12: =VLOOKUP(D12, AUXILIAR!$A$2:$B$16, 2, 0) -> LG Electronics | M12: =IF(AND(E12="Tecnología", J12>20000), "Prioridad Alta", IF(J12>5000, "Prioridad Media", "Prioridad Baja")) -> Prioridad Media | N12: =VLOOKUP(E12, AUXILIAR!$E$2:$F$4, 2, FALSE) -> ALM-03
A13: 416 | B13: 45707 | C13: CARLOS | D13: Licuadora de Mano | E13: Hogar | F13: Norte | G13: 14 | H13: 4896 | I13: 0.14 | J13: =G13*H13 -> 68544 | K13: =IF(J13>5000, "Venta Grande", "Venta Normal") -> Venta Grande | L13: =VLOOKUP(D13, AUXILIAR!$A$2:$B$16, 2, 0) -> LG Electronics | M13: =IF(AND(E13="Tecnología", J13>20000), "Prioridad Alta", IF(J13>5000, "Prioridad Media", "Prioridad Baja")) -> Prioridad Media | N13: =VLOOKUP(E13, AUXILIAR!$E$2:$F$4, 2, FALSE) -> ALM-02
A14: 482 | B14: 45773 | C14: LUIS | D14: Licuadora de Mano | E14: Hogar | F14: Sur | G14: 15 | H14: 4883 | I14: 0.12 | J14: =G14*H14 -> 73245 | K14: =IF(J14>5000, "Venta Grande", "Venta Normal") -> Venta Grande | L14: =VLOOKUP(D14, AUXILIAR!$A$2:$B$16, 2, 0) -> LG Electronics | M14: =IF(AND(E14="Tecnología", J14>20000), "Prioridad Alta", IF(J14>5000, "Prioridad Media", "Prioridad Baja")) -> Prioridad Media | N14: =VLOOKUP(E14, AUXILIAR!$E$2:$F$4, 2, FALSE) -> ALM-02
A15: 145 | B15: 45436 | C15: JUAN | D15: Celular Samsung | E15: Tecnología | F15: Oeste | G15: 13 | H15: 4882 | I15: 0.08 | J15: =G15*H15 -> 63466 | K15: =IF(J15>5000, "Venta Grande", "Venta Normal") -> Venta Grande | L15: =VLOOKUP(D15, AUXILIAR!$A$2:$B$16, 2, 0) -> Samsung Oficial | M15: =IF(AND(E15="Tecnología", J15>20000), "Prioridad Alta", IF(J15>5000, "Prioridad Media", "Prioridad Baja")) -> Prioridad Alta | N15: =VLOOKUP(E15, AUXILIAR!$E$2:$F$4, 2, FALSE) -> ALM-01
A16: 241 | B16: 45532 | C16: CARLOS | D16: Teclado Mecánico | E16: Oficina | F16: Norte | G16: 6 | H16: 4875 | I16: 0.12 | J16: =G16*H16 -> 29250 | K16: =IF(J16>5000, "Venta Grande", "Venta Normal") -> Venta Grande | L16: =VLOOKUP(D16, AUXILIAR!$A$2:$B$16, 2, 0) -> Samsung Oficial | M16: =IF(AND(E16="Tecnología", J16>20000), "Prioridad Alta", IF(J16>5000, "Prioridad Media", "Prioridad Baja")) -> Prioridad Media | N16: =VLOOKUP(E16, AUXILIAR!$E$2:$F$4, 2, FALSE) -> ALM-03
A17: 39 | B17: 45330 | C17: OSCAR | D17: Aspiradora Robot | E17: Hogar | F17: Este | G17: 16 | H17: 4849 | I17: 0.04 | J17: =G17*H17 -> 77584 | K17: =IF(J17>5000, "Venta Grande", "Venta Normal") -> Venta Grande | L17: =VLOOKUP(D17, AUXILIAR!$A$2:$B$16, 2, 0) -> Samsung Oficial | M17: =IF(AND(E17="Tecnología", J17>20000), "Prioridad Alta", IF(J17>5000, "Prioridad Media", "Prioridad Baja")) -> Prioridad Media | N17: =VLOOKUP(E17, AUXILIAR!$E$2:$F$4, 2, FALSE) -> ALM-02
A18: 17 | B18: 45308 | C18: LUIS | D18: Aspiradora Robot | E18: Hogar | F18: Sur | G18: 1 | H18: 3447 | I18: 0.09 | J18: =G18*H18 -> 3447 | K18: =IF(J18>5000, "Venta Grande", "Venta Normal") -> Venta Normal | L18: =VLOOKUP(D18, AUXILIAR!$A$2:$B$16, 2, 0) -> Samsung Oficial
A19: 247 | B19: 45538 | C19: LUIS | D19: Auriculares Bluetooth | E19: Tecnología | F19: Sur | G19: 20 | H19: 4844 | I19: 0.04 | J19: =G19*H19 -> 96880 | K19: =IF(J19>5000, "Venta Grande", "Venta Normal") -> Venta Grande | L19: =VLOOKUP(D19, AUXILIAR!$A$2:$B$16, 2, 0) -> LG Electronics | M19: =IF(AND(E19="Tecnología", J19>20000), "Prioridad Alta", IF(J19>5000, "Prioridad Media", "Prioridad Baja")) -> Prioridad Alta | N19: =VLOOKUP(E19, AUXILIAR!$E$2:$F$4, 2, FALSE) -> ALM-01
A20: 284 | B20: 45575 | C20: OSCAR | D20: Licuadora de Mano | E20: Hogar | F20: Este | G20: 19 | H20: 4833 | I20: 0.13 | J20: =G20*H20 -> 91827 | K20: =IF(J20>5000, "Venta Grande", "Venta Normal") -> Venta Grande | L20: =VLOOKUP(D20, AUXILIAR!$A$2:$B$16, 2, 0) -> LG Electronics | M20: =IF(AND(E20="Tecnología", J20>20000), "Prioridad Alta", IF(J20>5000, "Prioridad Media", "Prioridad Baja")) -> Prioridad Media | N20: =VLOOKUP(E20, AUXILIAR!$E$2:$F$4, 2, FALSE) -> ALM-02
A21: 209 | B21: 45500 | C21: OSCAR | D21: Smart TV 50" | E21: Tecnología | F21: Este | G21: 13 | H21: 4819 | I21: 0.08 | J21: =G21*H21 -> 62647 | K21: =IF(J21>5000, "Venta Grande", "Venta Normal") -> Venta Grande | L21: =VLOOKUP(D21, AUXILIAR!$A$2:$B$16, 2, 0) -> LG Electronics | M21: =IF(AND(E21="Tecnología", J21>20000), "Prioridad Alta", IF(J21>5000, "Prioridad Media", "Prioridad Baja")) -> Prioridad Alta | N21: =VLOOKUP(E21, AUXILIAR!$E$2:$F$4, 2, FALSE) -> ALM-01
A22: 382 | B22: 45673 | C22: LUIS | D22: Tablet Lenovo | E22: Tecnología | F22: Sur | G22: 19 | H22: 4817 | I22: 0.07 | J22: =G22*H22 -> 91523 | K22: =IF(J22>5000, "Venta Grande", "Venta Normal") -> Venta Grande | L22: =VLOOKUP(D22, AUXILIAR!$A$2:$B$16, 2, 0) -> Office Design | M22: =IF(AND(E22="Tecnología", J22>20000), "Prioridad Alta", IF(J22>5000, "Prioridad Media", "Prioridad Baja")) -> Prioridad Alta | N22: =VLOOKUP(E22, AUXILIAR!$E$2:$F$4, 2, FALSE) -> ALM-01
A23: 154 | B23: 45445 | C23: OSCAR | D23: Smart TV 50" | E23: Tecnología | F23: Este | G23: 16 | H23: 4789 | I23: 0.06 | J23: =G23*H23 -> 76624 | K23: =IF(J23>5000, "Venta Grande", "Venta Normal") -> Venta Grande | L23: =VLOOKUP(D23, AUXILIAR!$A$2:$B$16, 2, 0) -> LG Electronics | M23: =IF(AND(E23="Tecnología", J23>20000), "Prioridad Alta", IF(J23>5000, "Prioridad Media", "Prioridad Baja")) -> Prioridad Alta | N23: =VLOOKUP(E23, AUXILIAR!$E$2:$F$4, 2, FALSE) -> ALM-01
A24: 23 | B24: 45314 | C24: PEDRO | D24: Smart TV 50" | E24: Tecnología | F24: Centro | G24: 2 | H24: 272 | I24: 0.09 | J24: =G24*H24 -> 544 | K24: =IF(J24>5000, "Venta Grande", "Venta Normal") -> Venta Normal | L24: =VLOOKUP(D24, AUXILIAR!$A$2:$B$16, 2, 0) -> LG Electronics
A25: 208 | B25: 45499 | C25: PEDRO | D25: Teclado Mecánico | E25: Oficina | F25: Centro | G25: 7 | H25: 4787 | I25: 0.14 | J25: =G25*H25 -> 33509 | K25: =IF(J25>5000, "Venta Grande", "Venta Normal") -> Venta Grande | L25: =VLOOKUP(D25, AUXILIAR!$A$2:$B$16, 2, 0) -> Samsung Oficial | M25: =IF(AND(E25="Tecnología", J25>20000), "Prioridad Alta", IF(J25>5000, "Prioridad Media", "Prioridad Baja")) -> Prioridad Media | N25: =VLOOKUP(E25, AUXILIAR!$E$2:$F$4, 2, FALSE) -> ALM-03
A26: 50 | B26: 45341 | C26: JUAN | D26: Aspiradora Robot | E26: Hogar | F26: Oeste | G26: 14 | H26: 4780 | I26: 0.1 | J26: =G26*H26 -> 66920 | K26: =IF(J26>5000, "Venta Grande", "Venta Normal") -> Venta Grande | L26: =VLOOKUP(D26, AUXILIAR!$A$2:$B$16, 2, 0) -> Samsung Oficial | M26: =IF(AND(E26="Tecnología", J26>20000), "Prioridad Alta", IF(J26>5000, "Prioridad Media", "Prioridad Baja")) -> Prioridad Media | N26: =VLOOKUP(E26, AUXILIAR!$E$2:$F$4, 2, FALSE) -> ALM-02
A27: 458 | B27: 45749 | C27: PEDRO | D27: Silla Ergonómica | E27: Oficina | F27: Centro | G27: 15 | H27: 4777 | I27: 0.02 | J27: =G27*H27 -> 71655 | K27: =IF(J27>5000, "Venta Grande", "Venta Normal") -> Venta Grande | L27: =VLOOKUP(D27, AUXILIAR!$A$2:$B$16, 2, 0) -> LG Electronics | M27: =IF(AND(E27="Tecnología", J27>20000), "Prioridad Alta", IF(J27>5000, "Prioridad Media", "Prioridad Baja")) -> Prioridad Media | N27: =VLOOKUP(E27, AUXILIAR!$E$2:$F$4, 2, FALSE) -> ALM-03
A28: 125 | B28: 45416 | C28: JUAN | D28: Monitor 24" | E28: Oficina | F28: Oeste | G28: 4 | H28: 4769 | I28: 0.1 | J28: =G28*H28 -> 19076 | K28: =IF(J28>5000, "Venta Grande", "Venta Normal") -> Venta Grande | L28: =VLOOKUP(D28, AUXILIAR!$A$2:$B$16, 2, 0) -> Office Design | M28: =IF(AND(E28="Tecnología", J28>20000), "Prioridad Alta", IF(J28>5000, "Prioridad Media", "Prioridad Baja")) -> Prioridad Media | N28: =VLOOKUP(E28, AUXILIAR!$E$2:$F$4, 2, FALSE) -> ALM-03
A29: 49 | B29: 45340 | C29: OSCAR | D29: Auriculares Bluetooth | E29: Tecnología | F29: Este | G29: 7 | H29: 4763 | I29: 0.11 | J29: =G29*H29 -> 33341 | K29: =IF(J29>5000, "Venta Grande", "Venta Normal") -> Venta Grande | L29: =VLOOKUP(D29, AUXILIAR!$A$2:$B$16, 2, 0) -> LG Electronics | M29: =IF(AND(E29="Tecnología", J29>20000), "Prioridad Alta", IF(J29>5000, "Prioridad Media", "Prioridad Baja")) -> Prioridad Alta | N29: =VLOOKUP(E29, AUXILIAR!$E$2:$F$4, 2, FALSE) -> ALM-01
A30: 213 | B30: 45504 | C30: PEDRO | D30: Monitor 24" | E30: Oficina | F30: Centro | G30: 13 | H30: 4758 | I30: 0.12 | J30: =G30*H30 -> 61854 | K30: =IF(J30>5000, "Venta Grande", "Venta Normal") -> Venta Grande | L30: =VLOOKUP(D30, AUXILIAR!$A$2:$B$16, 2, 0) -> Office Design | M30: =IF(AND(E30="Tecnología", J30>20000), "Prioridad Alta", IF(J30>5000, "Prioridad Media", "Prioridad Baja")) -> Prioridad Media | N30: =VLOOKUP(E30, AUXILIAR!$E$2:$F$4, 2, FALSE) -> ALM-03
A31: 30 | B31: 45321 | C31: JUAN | D31: Tablet Lenovo | E31: Tecnología | F31: Oeste | G31: 10 | H31: 349 | I31: 0.04 | J31: =G31*H31 -> 3490 | K31: =IF(J31>5000, "Venta Grande", "Venta Normal") -> Venta Normal | L31: =VLOOKUP(D31, AUXILIAR!$A$2:$B$16, 2, 0) -> Office Design
A32: 271 | B32: 45562 | C32: CARLOS | D32: Silla Ergonómica | E32: Oficina | F32: Norte | G32: 7 | H32: 4744 | I32: 0.1 | J32: =G32*H32 -> 33208 | K32: =IF(J32>5000, "Venta Grande", "Venta Normal") -> Venta Grande | L32: =VLOOKUP(D32, AUXILIAR!$A$2:$B$16, 2, 0) -> LG Electronics | M32: =IF(AND(E32="Tecnología", J32>20000), "Prioridad Alta", IF(J32>5000, "Prioridad Media", "Prioridad Baja")) -> Prioridad Media | N32: =VLOOKUP(E32, AUXILIAR!$E$2:$F$4, 2, FALSE) -> ALM-03
A33: 197 | B33: 45488 | C33: LUIS | D33: Teclado Mecánico | E33: Oficina | F33: Sur | G33: 13 | H33: 4726 | I33: 0.11 | J33: =G33*H33 -> 61438 | K33: =IF(J33>5000, "Venta Grande", "Venta Normal") -> Venta Grande | L33: =VLOOKUP(D33, AUXILIAR!$A$2:$B$16, 2, 0) -> Samsung Oficial | M33: =IF(AND(E33="Tecnología", J33>20000), "Prioridad Alta", IF(J33>5000, "Prioridad Media", "Prioridad Baja")) -> Prioridad Media | N33: =VLOOKUP(E33, AUXILIAR!$E$2:$F$4, 2, FALSE) -> ALM-03
A34: 33 | B34: 45324 | C34: PEDRO | D34: Smart TV 50" | E34: Tecnología | F34: Centro | G34: 1 | H34: 3859 | I34: 0.15 | J34: =G34*H34 -> 3859 | K34: =IF(J34>5000, "Venta Grande", "Venta Normal") -> Venta Normal | L34: =VLOOKUP(D34, AUXILIAR!$A$2:$B$16, 2, 0) -> LG Electronics
A35: 366 | B35: 45657 | C35: CARLOS | D35: Cafetera Eléctrica | E35: Hogar | F35: Norte | G35: 2 | H35: 4721 | I35: 0.1 | J35: =G35*H35 -> 9442 | K35: =IF(J35>5000, "Venta Grande", "Venta Normal") -> Venta Grande | L35: =VLOOKUP(D35, AUXILIAR!$A$2:$B$16, 2, 0) -> LG Electronics | M35: =IF(AND(E35="Tecnología", J35>20000), "Prioridad Alta", IF(J35>5000, "Prioridad Media", "Prioridad Baja")) -> Prioridad Media | N35: =VLOOKUP(E35, AUXILIAR!$E$2:$F$4, 2, FALSE) -> ALM-02
A36: 155 | B36: 45446 | C36: JUAN | D36: Smart TV 50" | E36: Tecnología | F36: Oeste | G36: 10 | H36: 4686 | I36: 0.05 | J36: =G36*H36 -> 46860 | K36: =IF(J36>5000, "Venta Grande", "Venta Normal") -> Venta Grande | L36: =VLOOKUP(D36, AUXILIAR!$A$2:$B$16, 2, 0) -> LG Electronics | M36: =IF(AND(E36="Tecnología", J36>20000), "Prioridad Alta", IF(J36>5000, "Prioridad Media", "Prioridad Baja")) -> Prioridad Alta | N36: =VLOOKUP(E36, AUXILIAR!$E$2:$F$4, 2, FALSE) -> ALM-01
A37: 36 | B37: 45327 | C37: CARLOS | D37: Cafetera Eléctrica | E37: Hogar | F37: Norte | G37: 7 | H37: 146 | I37: 0.09 | J37: =G37*H37 -> 1022 | K37: =IF(J37>5000, "Venta Grande", "Venta Normal") -> Venta Normal | L37: =VLOOKUP(D37, AUXILIAR!$A$2:$B$16, 2, 0) -> LG Electronics
A38: 37 | B38: 45328 | C38: LUIS | D38: Monitor 24" | E38: Oficina | F38: Sur | G38: 3 | H38: 941 | I38: 0.03 | J38: =G38*H38 -> 2823 | K38: =IF(J38>5000, "Venta Grande", "Venta Normal") -> Venta Normal | L38: =VLOOKUP(D38, AUXILIAR!$A$2:$B$16, 2, 0) -> Office Design
A39: 354 | B39: 45645 | C39: OSCAR | D39: Celular Samsung | E39: Tecnología | F39: Este | G39: 6 | H39: 4656 | I39: 0.15 | J39: =G39*H39 -> 27936 | K39: =IF(J39>5000, "Venta Grande", "Venta Normal") -> Venta Grande | L39: =VLOOKUP(D39, AUXILIAR!$A$2:$B$16, 2, 0) -> Samsung Oficial | M39: =IF(AND(E39="Tecnología", J39>20000), "Prioridad Alta", IF(J39>5000, "Prioridad Media", "Prioridad Baja")) -> Prioridad Alta | N39: =VLOOKUP(E39, AUXILIAR!$E$2:$F$4, 2, FALSE) -> ALM-01
A40: 270 | B40: 45561 | C40: JUAN | D40: Aspiradora Robot | E40: Hogar | F40: Oeste | G40: 19 | H40: 4648 | I40: 0.09 | J40: =G40*H40 -> 88312 | K40: =IF(J40>5000, "Venta Grande", "Venta Normal") -> Venta Grande | L40: =VLOOKUP(D40, AUXILIAR!$A$2:$B$16, 2, 0) -> Samsung Oficial | M40: =IF(AND(E40="Tecnología", J40>20000), "Prioridad Alta", IF(J40>5000, "Prioridad Media", "Prioridad Baja")) -> Prioridad Media | N40: =VLOOKUP(E40, AUXILIAR!$E$2:$F$4, 2, FALSE) -> ALM-02
A41: 137 | B41: 45428 | C41: LUIS | D41: Auriculares Bluetooth | E41: Tecnología | F41: Sur | G41: 7 | H41: 4646 | I41: 0.05 | J41: =G41*H41 -> 32522 | K41: =IF(J41>5000, "Venta Grande", "Venta Normal") -> Venta Grande | L41: =VLOOKUP(D41, AUXILIAR!$A$2:$B$16, 2, 0) -> LG Electronics | M41: =IF(AND(E41="Tecnología", J41>20000), "Prioridad Alta", IF(J41>5000, "Prioridad Media", "Prioridad Baja")) -> Prioridad Alta | N41: =VLOOKUP(E41, AUXILIAR!$E$2:$F$4, 2, FALSE) -> ALM-01
A42: 375 | B42: 45666 | C42: JUAN | D42: Smart TV 50" | E42: Tecnología | F42: Oeste | G42: 19 | H42: 4638 | I42: 0.02 | J42: =G42*H42 -> 88122 | K42: =IF(J42>5000, "Venta Grande", "Venta Normal") -> Venta Grande | L42: =VLOOKUP(D42, AUXILIAR!$A$2:$B$16, 2, 0) -> LG Electronics | M42: =IF(AND(E42="Tecnología", J42>20000), "Prioridad Alta", IF(J42>5000, "Prioridad Media", "Prioridad Baja")) -> Prioridad Alta | N42: =VLOOKUP(E42, AUXILIAR!$E$2:$F$4, 2, FALSE) -> ALM-01
A43: 42 | B43: 45333 | C43: LUIS | D43: Licuadora de Mano | E43: Hogar | F43: Sur | G43: 3 | H43: 865 | I43: 0.1 | J43: =G43*H43 -> 2595 | K43: =IF(J43>5000, "Venta Grande", "Venta Normal") -> Venta Normal | L43: =VLOOKUP(D43, AUXILIAR!$A$2:$B$16, 2, 0) -> LG Electronics
A44: 212 | B44: 45503 | C44: LUIS | D44: Cafetera Eléctrica | E44: Hogar | F44: Sur | G44: 2 | H44: 4632 | I44: 0.12 | J44: =G44*H44 -> 9264 | K44: =IF(J44>5000, "Venta Grande", "Venta Normal") -> Venta Grande | L44: =VLOOKUP(D44, AUXILIAR!$A$2:$B$16, 2, 0) -> LG Electronics | M44: =IF(AND(E44="Tecnología", J44>20000), "Prioridad Alta", IF(J44>5000, "Prioridad Media", "Prioridad Baja")) -> Prioridad Media | N44: =VLOOKUP(E44, AUXILIAR!$E$2:$F$4, 2, FALSE) -> ALM-02
A45: 6 | B45: 45297 | C45: CARLOS | D45: Aspiradora Robot | E45: Hogar | F45: Norte | G45: 20 | H45: 4622 | I45: 0.09 | J45: =G45*H45 -> 92440 | K45: =IF(J45>5000, "Venta Grande", "Venta Normal") -> Venta Grande | L45: =VLOOKUP(D45, AUXILIAR!$A$2:$B$16, 2, 0) -> Samsung Oficial | M45: =IF(AND(E45="Tecnología", J45>20000), "Prioridad Alta", IF(J45>5000, "Prioridad Media", "Prioridad Baja")) -> Prioridad Media | N45: =VLOOKUP(E45, AUXILIAR!$E$2:$F$4, 2, FALSE) -> ALM-02
A46: 93 | B46: 45384 | C46: PEDRO | D46: Auriculares Bluetooth | E46: Tecnología | F46: Centro | G46: 20 | H46: 4611 | I46: 0.13 | J46: =G46*H46 -> 92220 | K46: =IF(J46>5000, "Venta Grande", "Venta Normal") -> Venta Grande | L46: =VLOOKUP(D46, AUXILIAR!$A$2:$B$16, 2, 0) -> LG Electronics | M46: =IF(AND(E46="Tecnología", J46>20000), "Prioridad Alta", IF(J46>5000, "Prioridad Media", "Prioridad Baja")) -> Prioridad Alta | N46: =VLOOKUP(E46, AUXILIAR!$E$2:$F$4, 2, FALSE) -> ALM-01
A47: 459 | B47: 45750 | C47: OSCAR | D47: Tablet Lenovo | E47: Tecnología | F47: Este | G47: 18 | H47: 4611 | I47: 0.03 | J47: =G47*H47 -> 82998 | K47: =IF(J47>5000, "Venta Grande", "Venta Normal") -> Venta Grande | L47: =VLOOKUP(D47, AUXILIAR!$A$2:$B$16, 2, 0) -> Office Design | M47: =IF(AND(E47="Tecnología", J47>20000), "Prioridad Alta", IF(J47>5000, "Prioridad Media", "Prioridad Baja")) -> Prioridad Alta | N47: =VLOOKUP(E47, AUXILIAR!$E$2:$F$4, 2, FALSE) -> ALM-01
A48: 47 | B48: 45338 | C48: LUIS | D48: Cafetera Eléctrica | E48: Hogar | F48: Sur | G48: 2 | H48: 1643 | I48: 0.04 | J48: =G48*H48 -> 3286 | K48: =IF(J48>5000, "Venta Grande", "Venta Normal") -> Venta Normal | L48: =VLOOKUP(D48, AUXILIAR!$A$2:$B$16, 2, 0) -> LG Electronics
A49: 45 | B49: 45336 | C49: JUAN | D49: Smart TV 50" | E49: Tecnología | F49: Oeste | G49: 20 | H49: 4606 | I49: 0.04 | J49: =G49*H49 -> 92120 | K49: =IF(J49>5000, "Venta Grande", "Venta Normal") -> Venta Grande | L49: =VLOOKUP(D49, AUXILIAR!$A$2:$B$16, 2, 0) -> LG Electronics | M49: =IF(AND(E49="Tecnología", J49>20000), "Prioridad Alta", IF(J49>5000, "Prioridad Media", "Prioridad Baja")) -> Prioridad Alta | N49: =VLOOKUP(E49, AUXILIAR!$E$2:$F$4, 2, FALSE) -> ALM-01
A50: 227 | B50: 45518 | C50: LUIS | D50: Silla Ergonómica | E50: Oficina | F50: Sur | G50: 20 | H50: 4604 | I50: 0.07 | J50: =G50*H50 -> 92080 | K50: =IF(J50>5000, "Venta Grande", "Venta Normal") -> Venta Grande | L50: =VLOOKUP(D50, AUXILIAR!$A$2:$B$16, 2, 0) -> LG Electronics | M50: =IF(AND(E50="Tecnología", J50>20000), "Prioridad Alta", IF(J50>5000, "Prioridad Media", "Prioridad Baja")) -> Prioridad Media | N50: =VLOOKUP(E50, AUXILIAR!$E$2:$F$4, 2, FALSE) -> ALM-03
A51: 262 | B51: 45553 | C51: LUIS | D51: Licuadora de Mano | E51: Hogar | F51: Sur | G51: 20 | H51: 4590 | I51: 0.12 | J51: =G51*H51 -> 91800 | K51: =IF(J51>5000, "Venta Grande", "Venta Normal") -> Venta Grande | L51: =VLOOKUP(D51, AUXILIAR!$A$2:$B$16, 2, 0) -> LG Electronics | M51: =IF(AND(E51="Tecnología", J51>20000), "Prioridad Alta", IF(J51>5000, "Prioridad Media", "Prioridad Baja")) -> Prioridad Media | N51: =VLOOKUP(E51, AUXILIAR!$E$2:$F$4, 2, FALSE) -> ALM-02
A52: 259 | B52: 45550 | C52: OSCAR | D52: Aspiradora Robot | E52: Hogar | F52: Este | G52: 19 | H52: 4576 | I52: 0.04 | J52: =G52*H52 -> 86944 | K52: =IF(J52>5000, "Venta Grande", "Venta Normal") -> Venta Grande | L52: =VLOOKUP(D52, AUXILIAR!$A$2:$B$16, 2, 0) -> Samsung Oficial | M52: =IF(AND(E52="Tecnología", J52>20000), "Prioridad Alta", IF(J52>5000, "Prioridad Media", "Prioridad Baja")) -> Prioridad Media | N52: =VLOOKUP(E52, AUXILIAR!$E$2:$F$4, 2, FALSE) -> ALM-02
A53: 273 | B53: 45564 | C53: PEDRO | D53: Licuadora de Mano | E53: Hogar | F53: Centro | G53: 17 | H53: 4559 | I53: 0.02 | J53: =G53*H53 -> 77503 | K53: =IF(J53>5000, "Venta Grande", "Venta Normal") -> Venta Grande | L53: =VLOOKUP(D53, AUXILIAR!$A$2:$B$16, 2, 0) -> LG Electronics | M53: =IF(AND(E53="Tecnología", J53>20000), "Prioridad Alta", IF(J53>5000, "Prioridad Media", "Prioridad Baja")) -> Prioridad Media | N53: =VLOOKUP(E53, AUXILIAR!$E$2:$F$4, 2, FALSE) -> ALM-02
A54: 130 | B54: 45421 | C54: JUAN | D54: Licuadora de Mano | E54: Hogar | F54: Oeste | G54: 13 | H54: 4553 | I54: 0.05 | J54: =G54*H54 -> 59189 | K54: =IF(J54>5000, "Venta Grande", "Venta Normal") -> Venta Grande | L54: =VLOOKUP(D54, AUXILIAR!$A$2:$B$16, 2, 0) -> LG Electronics | M54: =IF(AND(E54="Tecnología", J54>20000), "Prioridad Alta", IF(J54>5000, "Prioridad Media", "Prioridad Baja")) -> Prioridad Media | N54: =VLOOKUP(E54, AUXILIAR!$E$2:$F$4, 2, FALSE) -> ALM-02
A55: 297 | B55: 45588 | C55: LUIS | D55: Smart TV 50" | E55: Tecnología | F55: Sur | G55: 16 | H55: 4542 | I55: 0.13 | J55: =G55*H55 -> 72672 | K55: =IF(J55>5000, "Venta Grande", "Venta Normal") -> Venta Grande | L55: =VLOOKUP(D55, AUXILIAR!$A$2:$B$16, 2, 0) -> LG Electronics | M55: =IF(AND(E55="Tecnología", J55>20000), "Prioridad Alta", IF(J55>5000, "Prioridad Media", "Prioridad Baja")) -> Prioridad Alta | N55: =VLOOKUP(E55, AUXILIAR!$E$2:$F$4, 2, FALSE) -> ALM-01
A56: 106 | B56: 45397 | C56: CARLOS | D56: Silla Ergonómica | E56: Oficina | F56: Norte | G56: 19 | H56: 4534 | I56: 0.07 | J56: =G56*H56 -> 86146 | K56: =IF(J56>5000, "Venta Grande", "Venta Normal") -> Venta Grande | L56: =VLOOKUP(D56, AUXILIAR!$A$2:$B$16, 2, 0) -> LG Electronics | M56: =IF(AND(E56="Tecnología", J56>20000), "Prioridad Alta", IF(J56>5000, "Prioridad Media", "Prioridad Baja")) -> Prioridad Media | N56: =VLOOKUP(E56, AUXILIAR!$E$2:$F$4, 2, FALSE) -> ALM-03
A57: 327 | B57: 45618 | C57: LUIS | D57: Tablet Lenovo | E57: Tecnología | F57: Sur | G57: 3 | H57: 4531 | I57: 0.06 | J57: =G57*H57 -> 13593 | K57: =IF(J57>5000, "Venta Grande", "Venta Normal") -> Venta Grande | L57: =VLOOKUP(D57, AUXILIAR!$A$2:$B$16, 2, 0) -> Office Design | M57: =IF(AND(E57="Tecnología", J57>20000), "Prioridad Alta", IF(J57>5000, "Prioridad Media", "Prioridad Baja")) -> Prioridad Media | N57: =VLOOKUP(E57, AUXILIAR!$E$2:$F$4, 2, FALSE) -> ALM-01
A58: 424 | B58: 45715 | C58: OSCAR | D58: Aspiradora Robot | E58: Hogar | F58: Este | G58: 15 | H58: 4526 | I58: 0.07 | J58: =G58*H58 -> 67890 | K58: =IF(J58>5000, "Venta Grande", "Venta Normal") -> Venta Grande | L58: =VLOOKUP(D58, AUXILIAR!$A$2:$B$16, 2, 0) -> Samsung Oficial | M58: =IF(AND(E58="Tecnología", J58>20000), "Prioridad Alta", IF(J58>5000, "Prioridad Media", "Prioridad Baja")) -> Prioridad Media | N58: =VLOOKUP(E58, AUXILIAR!$E$2:$F$4, 2, FALSE) -> ALM-02
A59: 58 | B59: 45349 | C59: PEDRO | D59: Cafetera Eléctrica | E59: Hogar | F59: Centro | G59: 6 | H59: 694 | I59: 0.15 | J59: =G59*H59 -> 4164 | K59: =IF(J59>5000, "Venta Grande", "Venta Normal") -> Venta Normal | L59: =VLOOKUP(D59, AUXILIAR!$A$2:$B$16, 2, 0) -> LG Electronics
A60: 59 | B60: 45350 | C60: OSCAR | D60: Monitor 24" | E60: Oficina | F60: Este | G60: 1 | H60: 3724 | I60: 0.04 | J60: =G60*H60 -> 3724 | K60: =IF(J60>5000, "Venta Grande", "Venta Normal") -> Venta Normal | L60: =VLOOKUP(D60, AUXILIAR!$A$2:$B$16, 2, 0) -> Office Design
A61: 88 | B61: 45379 | C61: PEDRO | D61: Smart TV 50" | E61: Tecnología | F61: Centro | G61: 19 | H61: 4525 | I61: 0.04 | J61: =G61*H61 -> 85975 | K61: =IF(J61>5000, "Venta Grande", "Venta Normal") -> Venta Grande | L61: =VLOOKUP(D61, AUXILIAR!$A$2:$B$16, 2, 0) -> LG Electronics | M61: =IF(AND(E61="Tecnología", J61>20000), "Prioridad Alta", IF(J61>5000, "Prioridad Media", "Prioridad Baja")) -> Prioridad Alta | N61: =VLOOKUP(E61, AUXILIAR!$E$2:$F$4, 2, FALSE) -> ALM-01
A62: 285 | B62: 45576 | C62: JUAN | D62: Teclado Mecánico | E62: Oficina | F62: Oeste | G62: 20 | H62: 4516 | I62: 0.08 | J62: =G62*H62 -> 90320 | K62: =IF(J62>5000, "Venta Grande", "Venta Normal") -> Venta Grande | L62: =VLOOKUP(D62, AUXILIAR!$A$2:$B$16, 2, 0) -> Samsung Oficial | M62: =IF(AND(E62="Tecnología", J62>20000), "Prioridad Alta", IF(J62>5000, "Prioridad Media", "Prioridad Baja")) -> Prioridad Media | N62: =VLOOKUP(E62, AUXILIAR!$E$2:$F$4, 2, FALSE) -> ALM-03
A63: 491 | B63: 45782 | C63: CARLOS | D63: Silla Ergonómica | E63: Oficina | F63: Norte | G63: 15 | H63: 4504 | I63: 0.07 | J63: =G63*H63 -> 67560 | K63: =IF(J63>5000, "Venta Grande", "Venta Normal") -> Venta Grande | L63: =VLOOKUP(D63, AUXILIAR!$A$2:$B$16, 2, 0) -> LG Electronics | M63: =IF(AND(E63="Tecnología", J63>20000), "Prioridad Alta", IF(J63>5000, "Prioridad Media", "Prioridad Baja")) -> Prioridad Media | N63: =VLOOKUP(E63, AUXILIAR!$E$2:$F$4, 2, FALSE) -> ALM-03
A64: 63 | B64: 45354 | C64: PEDRO | D64: Tablet Lenovo | E64: Tecnología | F64: Centro | G64: 2 | H64: 469 | I64: 0.06 | J64: =G64*H64 -> 938 | K64: =IF(J64>5000, "Venta Grande", "Venta Normal") -> Venta Normal | L64: =VLOOKUP(D64, AUXILIAR!$A$2:$B$16, 2, 0) -> Office Design
A65: 487 | B65: 45778 | C65: LUIS | D65: Cafetera Eléctrica | E65: Hogar | F65: Sur | G65: 4 | H65: 4500 | I65: 0.07 | J65: =G65*H65 -> 18000 | K65: =IF(J65>5000, "Venta Grande", "Venta Normal") -> Venta Grande | L65: =VLOOKUP(D65, AUXILIAR!$A$2:$B$16, 2, 0) -> LG Electronics | M65: =IF(AND(E65="Tecnología", J65>20000), "Prioridad Alta", IF(J65>5000, "Prioridad Media", "Prioridad Baja")) -> Prioridad Media | N65: =VLOOKUP(E65, AUXILIAR!$E$2:$F$4, 2, FALSE) -> ALM-02
A66: 41 | B66: 45332 | C66: CARLOS | D66: Tablet Lenovo | E66: Tecnología | F66: Norte | G66: 6 | H66: 4496 | I66: 0.04 | J66: =G66*H66 -> 26976 | K66: =IF(J66>5000, "Venta Grande", "Venta Normal") -> Venta Grande | L66: =VLOOKUP(D66, AUXILIAR!$A$2:$B$16, 2, 0) -> Office Design | M66: =IF(AND(E66="Tecnología", J66>20000), "Prioridad Alta", IF(J66>5000, "Prioridad Media", "Prioridad Baja")) -> Prioridad Alta | N66: =VLOOKUP(E66, AUXILIAR!$E$2:$F$4, 2, FALSE) -> ALM-01
A67: 433 | B67: 45724 | C67: PEDRO | D67: Monitor 24" | E67: Oficina | F67: Centro | G67: 3 | H67: 4491 | I67: 0.07 | J67: =G67*H67 -> 13473 | K67: =IF(J67>5000, "Venta Grande", "Venta Normal") -> Venta Grande | L67: =VLOOKUP(D67, AUXILIAR!$A$2:$B$16, 2, 0) -> Office Design | M67: =IF(AND(E67="Tecnología", J67>20000), "Prioridad Alta", IF(J67>5000, "Prioridad Media", "Prioridad Baja")) -> Prioridad Media | N67: =VLOOKUP(E67, AUXILIAR!$E$2:$F$4, 2, FALSE) -> ALM-03
A68: 43 | B68: 45334 | C68: PEDRO | D68: Teclado Mecánico | E68: Oficina | F68: Centro | G68: 14 | H68: 4478 | I68: 0.14 | J68: =G68*H68 -> 62692 | K68: =IF(J68>5000, "Venta Grande", "Venta Normal") -> Venta Grande | L68: =VLOOKUP(D68, AUXILIAR!$A$2:$B$16, 2, 0) -> Samsung Oficial | M68: =IF(AND(E68="Tecnología", J68>20000), "Prioridad Alta", IF(J68>5000, "Prioridad Media", "Prioridad Baja")) -> Prioridad Media | N68: =VLOOKUP(E68, AUXILIAR!$E$2:$F$4, 2, FALSE) -> ALM-03
A69: 82 | B69: 45373 | C69: LUIS | D69: Auriculares Bluetooth | E69: Tecnología | F69: Sur | G69: 17 | H69: 4466 | I69: 0.13 | J69: =G69*H69 -> 75922 | K69: =IF(J69>5000, "Venta Grande", "Venta Normal") -> Venta Grande | L69: =VLOOKUP(D69, AUXILIAR!$A$2:$B$16, 2, 0) -> LG Electronics | M69: =IF(AND(E69="Tecnología", J69>20000), "Prioridad Alta", IF(J69>5000, "Prioridad Media", "Prioridad Baja")) -> Prioridad Alta | N69: =VLOOKUP(E69, AUXILIAR!$E$2:$F$4, 2, FALSE) -> ALM-01
A70: 69 | B70: 45360 | C70: OSCAR | D70: Cafetera Eléctrica | E70: Hogar | F70: Este | G70: 1 | H70: 266 | I70: 0.02 | J70: =G70*H70 -> 266 | K70: =IF(J70>5000, "Venta Grande", "Venta Normal") -> Venta Normal | L70: =VLOOKUP(D70, AUXILIAR!$A$2:$B$16, 2, 0) -> LG Electronics
A71: 360 | B71: 45651 | C71: JUAN | D71: Tablet Lenovo | E71: Tecnología | F71: Oeste | G71: 20 | H71: 4452 | I71: 0.06 | J71: =G71*H71 -> 89040 | K71: =IF(J71>5000, "Venta Grande", "Venta Normal") -> Venta Grande | L71: =VLOOKUP(D71, AUXILIAR!$A$2:$B$16, 2, 0) -> Office Design | M71: =IF(AND(E71="Tecnología", J71>20000), "Prioridad Alta", IF(J71>5000, "Prioridad Media", "Prioridad Baja")) -> Prioridad Alta | N71: =VLOOKUP(E71, AUXILIAR!$E$2:$F$4, 2, FALSE) -> ALM-01
A72: 71 | B72: 45362 | C72: CARLOS | D72: Auriculares Bluetooth | E72: Tecnología | F72: Norte | G72: 6 | H72: 482 | I72: 0.15 | J72: =G72*H72 -> 2892 | K72: =IF(J72>5000, "Venta Grande", "Venta Normal") -> Venta Normal | L72: =VLOOKUP(D72, AUXILIAR!$A$2:$B$16, 2, 0) -> LG Electronics
A73: 409 | B73: 45700 | C73: OSCAR | D73: Celular Samsung | E73: Tecnología | F73: Este | G73: 4 | H73: 4446 | I73: 0.05 | J73: =G73*H73 -> 17784 | K73: =IF(J73>5000, "Venta Grande", "Venta Normal") -> Venta Grande | L73: =VLOOKUP(D73, AUXILIAR!$A$2:$B$16, 2, 0) -> Samsung Oficial | M73: =IF(AND(E73="Tecnología", J73>20000), "Prioridad Alta", IF(J73>5000, "Prioridad Media", "Prioridad Baja")) -> Prioridad Media | N73: =VLOOKUP(E73, AUXILIAR!$E$2:$F$4, 2, FALSE) -> ALM-01
A74: 210 | B74: 45501 | C74: JUAN | D74: Smart TV 50" | E74: Tecnología | F74: Oeste | G74: 6 | H74: 4445 | I74: 0.08 | J74: =G74*H74 -> 26670 | K74: =IF(J74>5000, "Venta Grande", "Venta Normal") -> Venta Grande | L74: =VLOOKUP(D74, AUXILIAR!$A$2:$B$16, 2, 0) -> LG Electronics | M74: =IF(AND(E74="Tecnología", J74>20000), "Prioridad Alta", IF(J74>5000, "Prioridad Media", "Prioridad Baja")) -> Prioridad Alta | N74: =VLOOKUP(E74, AUXILIAR!$E$2:$F$4, 2, FALSE) -> ALM-01
A75: 74 | B75: 45365 | C75: OSCAR | D75: Tablet Lenovo | E75: Tecnología | F75: Este | G75: 8 | H75: 225 | I75: 0.11 | J75: =G75*H75 -> 1800 | K75: =IF(J75>5000, "Venta Grande", "Venta Normal") -> Venta Normal | L75: =VLOOKUP(D75, AUXILIAR!$A$2:$B$16, 2, 0) -> Office Design
A76: 75 | B76: 45366 | C76: JUAN | D76: Licuadora de Mano | E76: Hogar | F76: Oeste | G76: 9 | H76: 256 | I76: 0.03 | J76: =G76*H76 -> 2304 | K76: =IF(J76>5000, "Venta Grande", "Venta Normal") -> Venta Normal | L76: =VLOOKUP(D76, AUXILIAR!$A$2:$B$16, 2, 0) -> LG Electronics
A77: 311 | B77: 45602 | C77: CARLOS | D77: Cafetera Eléctrica | E77: Hogar | F77: Norte | G77: 7 | H77: 4440 | I77: 0.04 | J77: =G77*H77 -> 31080 | K77: =IF(J77>5000, "Venta Grande", "Venta Normal") -> Venta Grande | L77: =VLOOKUP(D77, AUXILIAR!$A$2:$B$16, 2, 0) -> LG Electronics | M77: =IF(AND(E77="Tecnología", J77>20000), "Prioridad Alta", IF(J77>5000, "Prioridad Media", "Prioridad Baja")) -> Prioridad Media | N77: =VLOOKUP(E77, AUXILIAR!$E$2:$F$4, 2, FALSE) -> ALM-02
A78: 221 | B78: 45512 | C78: CARLOS | D78: Smart TV 50" | E78: Tecnología | F78: Norte | G78: 12 | H78: 4418 | I78: 0.03 | J78: =G78*H78 -> 53016 | K78: =IF(J78>5000, "Venta Grande", "Venta Normal") -> Venta Grande | L78: =VLOOKUP(D78, AUXILIAR!$A$2:$B$16, 2, 0) -> LG Electronics | M78: =IF(AND(E78="Tecnología", J78>20000), "Prioridad Alta", IF(J78>5000, "Prioridad Media", "Prioridad Baja")) -> Prioridad Alta | N78: =VLOOKUP(E78, AUXILIAR!$E$2:$F$4, 2, FALSE) -> ALM-01
A79: 4 | B79: 45295 | C79: OSCAR | D79: Monitor 24" | E79: Oficina | F79: Este | G79: 16 | H79: 4398 | I79: 0.05 | J79: =G79*H79 -> 70368 | K79: =IF(J79>5000, "Venta Grande", "Venta Normal") -> Venta Grande | L79: =VLOOKUP(D79, AUXILIAR!$A$2:$B$16, 2, 0) -> Office Design | M79: =IF(AND(E79="Tecnología", J79>20000), "Prioridad Alta", IF(J79>5000, "Prioridad Media", "Prioridad Baja")) -> Prioridad Media | N79: =VLOOKUP(E79, AUXILIAR!$E$2:$F$4, 2, FALSE) -> ALM-03
A80: 331 | B80: 45622 | C80: CARLOS | D80: Smart TV 50" | E80: Tecnología | F80: Norte | G80: 20 | H80: 4386 | I80: 0.07 | J80: =G80*H80 -> 87720 | K80: =IF(J80>5000, "Venta Grande", "Venta Normal") -> Venta Grande | L80: =VLOOKUP(D80, AUXILIAR!$A$2:$B$16, 2, 0) -> LG Electronics | M80: =IF(AND(E80="Tecnología", J80>20000), "Prioridad Alta", IF(J80>5000, "Prioridad Media", "Prioridad Baja")) -> Prioridad Alta | N80: =VLOOKUP(E80, AUXILIAR!$E$2:$F$4, 2, FALSE) -> ALM-01
A81: 80 | B81: 45371 | C81: JUAN | D81: Cafetera Eléctrica | E81: Hogar | F81: Oeste | G81: 10 | H81: 285 | I81: 0.08 | J81: =G81*H81 -> 2850 | K81: =IF(J81>5000, "Venta Grande", "Venta Normal") -> Venta Normal | L81: =VLOOKUP(D81, AUXILIAR!$A$2:$B$16, 2, 0) -> LG Electronics
A82: 167 | B82: 45458 | C82: LUIS | D82: Celular Samsung | E82: Tecnología | F82: Sur | G82: 15 | H82: 4381 | I82: 0.12 | J82: =G82*H82 -> 65715 | K82: =IF(J82>5000, "Venta Grande", "Venta Normal") -> Venta Grande | L82: =VLOOKUP(D82, AUXILIAR!$A$2:$B$16, 2, 0) -> Samsung Oficial | M82: =IF(AND(E82="Tecnología", J82>20000), "Prioridad Alta", IF(J82>5000, "Prioridad Media", "Prioridad Baja")) -> Prioridad Alta | N82: =VLOOKUP(E82, AUXILIAR!$E$2:$F$4, 2, FALSE) -> ALM-01
A83: 20 | B83: 45311 | C83: JUAN | D83: Licuadora de Mano | E83: Hogar | F83: Oeste | G83: 2 | H83: 4380 | I83: 0.04 | J83: =G83*H83 -> 8760 | K83: =IF(J83>5000, "Venta Grande", "Venta Normal") -> Venta Grande | L83: =VLOOKUP(D83, AUXILIAR!$A$2:$B$16, 2, 0) -> LG Electronics | M83: =IF(AND(E83="Tecnología", J83>20000), "Prioridad Alta", IF(J83>5000, "Prioridad Media", "Prioridad Baja")) -> Prioridad Media | N83: =VLOOKUP(E83, AUXILIAR!$E$2:$F$4, 2, FALSE) -> ALM-02
A84: 27 | B84: 45318 | C84: LUIS | D84: Auriculares Bluetooth | E84: Tecnología | F84: Sur | G84: 9 | H84: 4358 | I84: 0.04 | J84: =G84*H84 -> 39222 | K84: =IF(J84>5000, "Venta Grande", "Venta Normal") -> Venta Grande | L84: =VLOOKUP(D84, AUXILIAR!$A$2:$B$16, 2, 0) -> LG Electronics | M84: =IF(AND(E84="Tecnología", J84>20000), "Prioridad Alta", IF(J84>5000, "Prioridad Media", "Prioridad Baja")) -> Prioridad Alta | N84: =VLOOKUP(E84, AUXILIAR!$E$2:$F$4, 2, FALSE) -> ALM-01
A85: 228 | B85: 45519 | C85: PEDRO | D85: Tablet Lenovo | E85: Tecnología | F85: Centro | G85: 9 | H85: 4335 | I85: 0.03 | J85: =G85*H85 -> 39015 | K85: =IF(J85>5000, "Venta Grande", "Venta Normal") -> Venta Grande | L85: =VLOOKUP(D85, AUXILIAR!$A$2:$B$16, 2, 0) -> Office Design | M85: =IF(AND(E85="Tecnología", J85>20000), "Prioridad Alta", IF(J85>5000, "Prioridad Media", "Prioridad Baja")) -> Prioridad Alta | N85: =VLOOKUP(E85, AUXILIAR!$E$2:$F$4, 2, FALSE) -> ALM-01
A86: 406 | B86: 45697 | C86: CARLOS | D86: Teclado Mecánico | E86: Oficina | F86: Norte | G86: 14 | H86: 4305 | I86: 0.07 | J86: =G86*H86 -> 60270 | K86: =IF(J86>5000, "Venta Grande", "Venta Normal") -> Venta Grande | L86: =VLOOKUP(D86, AUXILIAR!$A$2:$B$16, 2, 0) -> Samsung Oficial | M86: =IF(AND(E86="Tecnología", J86>20000), "Prioridad Alta", IF(J86>5000, "Prioridad Media", "Prioridad Baja")) -> Prioridad Media | N86: =VLOOKUP(E86, AUXILIAR!$E$2:$F$4, 2, FALSE) -> ALM-03
A87: 85 | B87: 45376 | C87: JUAN | D87: Tablet Lenovo | E87: Tecnología | F87: Oeste | G87: 18 | H87: 4295 | I87: 0.11 | J87: =G87*H87 -> 77310 | K87: =IF(J87>5000, "Venta Grande", "Venta Normal") -> Venta Grande | L87: =VLOOKUP(D87, AUXILIAR!$A$2:$B$16, 2, 0) -> Office Design | M87: =IF(AND(E87="Tecnología", J87>20000), "Prioridad Alta", IF(J87>5000, "Prioridad Media", "Prioridad Baja")) -> Prioridad Alta | N87: =VLOOKUP(E87, AUXILIAR!$E$2:$F$4, 2, FALSE) -> ALM-01
A88: 258 | B88: 45549 | C88: PEDRO | D88: Auriculares Bluetooth | E88: Tecnología | F88: Centro | G88: 8 | H88: 4294 | I88: 0.04 | J88: =G88*H88 -> 34352 | K88: =IF(J88>5000, "Venta Grande", "Venta Normal") -> Venta Grande | L88: =VLOOKUP(D88, AUXILIAR!$A$2:$B$16, 2, 0) -> LG Electronics | M88: =IF(AND(E88="Tecnología", J88>20000), "Prioridad Alta", IF(J88>5000, "Prioridad Media", "Prioridad Baja")) -> Prioridad Alta | N88: =VLOOKUP(E88, AUXILIAR!$E$2:$F$4, 2, FALSE) -> ALM-01
A89: 379 | B89: 45670 | C89: OSCAR | D89: Auriculares Bluetooth | E89: Tecnología | F89: Este | G89: 11 | H89: 4285 | I89: 0.15 | J89: =G89*H89 -> 47135 | K89: =IF(J89>5000, "Venta Grande", "Venta Normal") -> Venta Grande | L89: =VLOOKUP(D89, AUXILIAR!$A$2:$B$16, 2, 0) -> LG Electronics | M89: =IF(AND(E89="Tecnología", J89>20000), "Prioridad Alta", IF(J89>5000, "Prioridad Media", "Prioridad Baja")) -> Prioridad Alta | N89: =VLOOKUP(E89, AUXILIAR!$E$2:$F$4, 2, FALSE) -> ALM-01
A90: 121 | B90: 45412 | C90: CARLOS | D90: Smart TV 50" | E90: Tecnología | F90: Norte | G90: 2 | H90: 4283 | I90: 0.04 | J90: =G90*H90 -> 8566 | K90: =IF(J90>5000, "Venta Grande", "Venta Normal") -> Venta Grande | L90: =VLOOKUP(D90, AUXILIAR!$A$2:$B$16, 2, 0) -> LG Electronics | M90: =IF(AND(E90="Tecnología", J90>20000), "Prioridad Alta", IF(J90>5000, "Prioridad Media", "Prioridad Baja")) -> Prioridad Media | N90: =VLOOKUP(E90, AUXILIAR!$E$2:$F$4, 2, FALSE) -> ALM-01
A91: 466 | B91: 45757 | C91: CARLOS | D91: Monitor 24" | E91: Oficina | F91: Norte | G91: 10 | H91: 4279 | I91: 0.11 | J91: =G91*H91 -> 42790 | K91: =IF(J91>5000, "Venta Grande", "Venta Normal") -> Venta Grande | L91: =VLOOKUP(D91, AUXILIAR!$A$2:$B$16, 2, 0) -> Office Design | M91: =IF(AND(E91="Tecnología", J91>20000), "Prioridad Alta", IF(J91>5000, "Prioridad Media", "Prioridad Baja")) -> Prioridad Media | N91: =VLOOKUP(E91, AUXILIAR!$E$2:$F$4, 2, FALSE) -> ALM-03
A92: 28 | B92: 45319 | C92: PEDRO | D92: Aspiradora Robot | E92: Hogar | F92: Centro | G92: 7 | H92: 4268 | I92: 0.07 | J92: =G92*H92 -> 29876 | K92: =IF(J92>5000, "Venta Grande", "Venta Normal") -> Venta Grande | L92: =VLOOKUP(D92, AUXILIAR!$A$2:$B$16, 2, 0) -> Samsung Oficial | M92: =IF(AND(E92="Tecnología", J92>20000), "Prioridad Alta", IF(J92>5000, "Prioridad Media", "Prioridad Baja")) -> Prioridad Media | N92: =VLOOKUP(E92, AUXILIAR!$E$2:$F$4, 2, FALSE) -> ALM-02
A93: 488 | B93: 45779 | C93: PEDRO | D93: Monitor 24" | E93: Oficina | F93: Centro | G93: 3 | H93: 4242 | I93: 0.05 | J93: =G93*H93 -> 12726 | K93: =IF(J93>5000, "Venta Grande", "Venta Normal") -> Venta Grande | L93: =VLOOKUP(D93, AUXILIAR!$A$2:$B$16, 2, 0) -> Office Design | M93: =IF(AND(E93="Tecnología", J93>20000), "Prioridad Alta", IF(J93>5000, "Prioridad Media", "Prioridad Baja")) -> Prioridad Media | N93: =VLOOKUP(E93, AUXILIAR!$E$2:$F$4, 2, FALSE) -> ALM-03
A94: 467 | B94: 45758 | C94: LUIS | D94: Auriculares Bluetooth | E94: Tecnología | F94: Sur | G94: 4 | H94: 4239 | I94: 0.05 | J94: =G94*H94 -> 16956 | K94: =IF(J94>5000, "Venta Grande", "Venta Normal") -> Venta Grande | L94: =VLOOKUP(D94, AUXILIAR!$A$2:$B$16, 2, 0) -> LG Electronics | M94: =IF(AND(E94="Tecnología", J94>20000), "Prioridad Alta", IF(J94>5000, "Prioridad Media", "Prioridad Baja")) -> Prioridad Media | N94: =VLOOKUP(E94, AUXILIAR!$E$2:$F$4, 2, FALSE) -> ALM-01
A95: 94 | B95: 45385 | C95: OSCAR | D95: Aspiradora Robot | E95: Hogar | F95: Este | G95: 2 | H95: 1664 | I95: 0.09 | J95: =G95*H95 -> 3328 | K95: =IF(J95>5000, "Venta Grande", "Venta Normal") -> Venta Normal | L95: =VLOOKUP(D95, AUXILIAR!$A$2:$B$16, 2, 0) -> Samsung Oficial
A96: 281 | B96: 45572 | C96: CARLOS | D96: Aspiradora Robot | E96: Hogar | F96: Norte | G96: 7 | H96: 4226 | I96: 0.04 | J96: =G96*H96 -> 29582 | K96: =IF(J96>5000, "Venta Grande", "Venta Normal") -> Venta Grande | L96: =VLOOKUP(D96, AUXILIAR!$A$2:$B$16, 2, 0) -> Samsung Oficial | M96: =IF(AND(E96="Tecnología", J96>20000), "Prioridad Alta", IF(J96>5000, "Prioridad Media", "Prioridad Baja")) -> Prioridad Media | N96: =VLOOKUP(E96, AUXILIAR!$E$2:$F$4, 2, FALSE) -> ALM-02
A97: 108 | B97: 45399 | C97: PEDRO | D97: Licuadora de Mano | E97: Hogar | F97: Centro | G97: 12 | H97: 4209 | I97: 0.09 | J97: =G97*H97 -> 50508 | K97: =IF(J97>5000, "Venta Grande", "Venta Normal") -> Venta Grande | L97: =VLOOKUP(D97, AUXILIAR!$A$2:$B$16, 2, 0) -> LG Electronics | M97: =IF(AND(E97="Tecnología", J97>20000), "Prioridad Alta", IF(J97>5000, "Prioridad Media", "Prioridad Baja")) -> Prioridad Media | N97: =VLOOKUP(E97, AUXILIAR!$E$2:$F$4, 2, FALSE) -> ALM-02
A98: 333 | B98: 45624 | C98: PEDRO | D98: Cafetera Eléctrica | E98: Hogar | F98: Centro | G98: 11 | H98: 4203 | I98: 0.07 | J98: =G98*H98 -> 46233 | K98: =IF(J98>5000, "Venta Grande", "Venta Normal") -> Venta Grande | L98: =VLOOKUP(D98, AUXILIAR!$A$2:$B$16, 2, 0) -> LG Electronics | M98: =IF(AND(E98="Tecnología", J98>20000), "Prioridad Alta", IF(J98>5000, "Prioridad Media", "Prioridad Baja")) -> Prioridad Media | N98: =VLOOKUP(E98, AUXILIAR!$E$2:$F$4, 2, FALSE) -> ALM-02
A99: 374 | B99: 45665 | C99: OSCAR | D99: Smart TV 50" | E99: Tecnología | F99: Este | G99: 20 | H99: 4187 | I99: 0.05 | J99: =G99*H99 -> 83740 | K99: =IF(J99>5000, "Venta Grande", "Venta Normal") -> Venta Grande | L99: =VLOOKUP(D99, AUXILIAR!$A$2:$B$16, 2, 0) -> LG Electronics | M99: =IF(AND(E99="Tecnología", J99>20000), "Prioridad Alta", IF(J99>5000, "Prioridad Media", "Prioridad Baja")) -> Prioridad Alta | N99: =VLOOKUP(E99, AUXILIAR!$E$2:$F$4, 2, FALSE) -> ALM-01
A100: 24 | B100: 45315 | C100: OSCAR | D100: Celular Samsung | E100: Tecnología | F100: Este | G100: 17 | H100: 4185 | I100: 0.11 | J100: =G100*H100 -> 71145 | K100: =IF(J100>5000, "Venta Grande", "Venta Normal") -> Venta Grande | L100: =VLOOKUP(D100, AUXILIAR!$A$2:$B$16, 2, 0) -> Samsung Oficial | M100: =IF(AND(E100="Tecnología", J100>20000), "Prioridad Alta", IF(J100>5000, "Prioridad Media", "Prioridad Baja")) -> Prioridad Alta | N100: =VLOOKUP(E100, AUXILIAR!$E$2:$F$4, 2, FALSE) -> ALM-01
...

Sheet TABLA DINAMICA
A3: Etiquetas de fila | B3: Suma de TOTAL_VENTA
A4: Centro | B4: 2673191
A5: Este | B5: 2723370
A6: Norte | B6: 2681744
A7: Oeste | B7: 2783006
A8: Sur | B8: 2703682
A9: Total general | B9: 13564993
A11: Etiquetas de fila | B11: Suma de TOTAL_VENTA
A12: Tecnología | B12: 6065320
A13: Oficina | B13: 3514129
A14: Hogar | B14: 3985544
A15: Total general | B15: 13564993
A17: Etiquetas de fila | B17: Suma de TOTAL_VENTA
A18: Prioridad Alta | B18: 5016839
A19: Prioridad Media | B19: 8316339
A20: Total general | B20: 13333178

Sheet DASHBOARD
A1: VENTAS TOTALES | F1: PRODUCTOS VENDIDOS | L1: TOTAL DE VENTAS
B2: =SUM('TABLA PRINCIPAL'!J:J) -> 27129986 | G2: =SUM('TABLA PRINCIPAL'!G:G) -> 5315 | L2: =COUNTA('TABLA PRINCIPAL'!A:A)-1 -> 502

Sheet AUXILIAR
A1: Producto | B1: Proveedor | E1: Celda E (Categoría) | F1: Celda F (ID_Almacén)
A2: Smart TV 50" | B2: LG Electronics | E2: Tecnología | F2: ALM-01
A3: Celular Samsung | B3: Samsung Oficial | E3: Hogar | F3: ALM-02
A4: Cafetera Eléctrica | B4: LG Electronics | E4: Oficina | F4: ALM-03
A5: Monitor 24" | B5: Office Design
A6: Auriculares Bluetooth | B6: LG Electronics
A7: Aspiradora Robot | B7: Samsung Oficial
A8: Silla Ergonómica | B8: LG Electronics
A9: Tablet Lenovo | B9: Office Design
A10: Licuadora de Mano | B10: LG Electronics
A11: Teclado Mecánico | B11: Samsung Oficial
A12: Smart TV 50" | B12: LG Electronics
A14: SUR
A15: CENTRO
A16: ESTE
A17: OESTE
